muna/__init__.py
muna/client.py
muna/compile.py
muna/logging.py
muna/muna.py
muna/sandbox.py
muna/version.py
muna/beta/__init__.py
muna/beta/annotations.py
muna/beta/client.py
muna/beta/metadata/__init__.py
muna/beta/metadata/_torch.py
muna/beta/metadata/coreml.py
muna/beta/metadata/executorch.py
muna/beta/metadata/iree.py
muna/beta/metadata/litert.py
muna/beta/metadata/llama.py
muna/beta/metadata/onnx.py
muna/beta/metadata/onnxruntime.py
muna/beta/metadata/openvino.py
muna/beta/metadata/qnn.py
muna/beta/metadata/tensorrt.py
muna/beta/metadata/tensorrt_rtx.py
muna/beta/metadata/tflite.py
muna/beta/openai/__init__.py
muna/beta/openai/audio.py
muna/beta/openai/chat.py
muna/beta/openai/completions.py
muna/beta/openai/embeddings.py
muna/beta/openai/openai.py
muna/beta/openai/schema.py
muna/beta/openai/speech.py
muna/beta/openai/transcription.py
muna/beta/remote/__init__.py
muna/beta/remote/endpoint.py
muna/beta/remote/prediction.py
muna/beta/remote/remote.py
muna/beta/remote/schema.py
muna/c/__init__.py
muna/c/configuration.py
muna/c/fxnc.py
muna/c/map.py
muna/c/prediction.py
muna/c/predictor.py
muna/c/stream.py
muna/c/value.py
muna/cli/__init__.py
muna/cli/auth.py
muna/cli/compile.py
muna/cli/misc.py
muna/cli/predictions.py
muna/cli/predictors.py
muna/cli/resources.py
muna/cli/sources.py
muna/cli/triage.py
muna/lib/__init__.py
muna/lib/linux/arm64/libFunction.so
muna/lib/linux/x86_64/libFunction.so
muna/lib/macos/arm64/Function.dylib
muna/lib/windows/arm64/Function.dll
muna/lib/windows/x86_64/Function.dll
muna/services/__init__.py
muna/services/prediction.py
muna/services/predictor.py
muna/services/user.py
muna/types/__init__.py
muna/types/parameter.py
muna/types/prediction.py
muna/types/predictor.py
muna/types/user.py
muna/types/value.py
muna-0.0.87.dist-info/licenses/LICENSE
muna-0.0.87.dist-info/METADATA
muna-0.0.87.dist-info/WHEEL
muna-0.0.87.dist-info/entry_points.txt
muna-0.0.87.dist-info/top_level.txt
muna-0.0.87.dist-info/RECORD
