Metadata-Version: 2.4
Name: muna
Version: 0.0.87
Summary: Run AI models in Python. Register at https://muna.ai.
Author-email: "NatML Inc." <hi@muna.ai>
License:                                  Apache License
Project-URL: Homepage, https://muna.ai
Project-URL: Documentation, https://docs.muna.ai
Project-URL: Source, https://github.com/muna-ai/muna-py
Project-URL: Changelog, https://github.com/muna-ai/muna-py/blob/main/Changelog.md
Classifier: Programming Language :: Python :: 3
Classifier: License :: OSI Approved :: Apache Software License
Classifier: Operating System :: OS Independent
Classifier: Topic :: Scientific/Engineering :: Image Recognition
Classifier: Topic :: Software Development :: Libraries
Requires-Python: >=3.11
License-File: LICENSE
Requires-Dist: numpy
Requires-Dist: pillow
Requires-Dist: pydantic>=2.0
Requires-Dist: requests
Requires-Dist: rich
Requires-Dist: typer
Dynamic: license-file
